{
  "gerado_em": "2026-07-10T20:37:25.608757-03:00",
  "data_alvo": "2026-07-11",
  "fonte": "Open-Meteo",
  "pontos": {
    "barra_recreio": {
      "nome": "Barra/Recreio",
      "temp_min_c": 18,
      "temp_max_janela_c": 19,
      "temp_med_c": 18,
      "sensacao_min_c": 19,
      "sensacao_largada_c": 20,
      "sensacao_final_c": 21,
      "umidade_max_pct": 98,
      "visibilidade_min_m": 120.0,
      "risco_neblina": "alto",
      "chuva_prob_max_pct": 0,
      "chuva_mm_total": 0.0,
      "chuva_mm_madrugada_antes": 0.0,
      "vento_med_kmh": 5.3,
      "rajada_max_kmh": 13.3,
      "vento_dir_graus": 341,
      "vento_dir_cardeal": "N",
      "nascer_do_sol": "06:35",
      "ok": true
    },
    "zona_sul": {
      "nome": "Zona Sul",
      "temp_min_c": 18,
      "temp_max_janela_c": 19,
      "temp_med_c": 18,
      "sensacao_min_c": 20,
      "sensacao_largada_c": 20,
      "sensacao_final_c": 22,
      "umidade_max_pct": 94,
      "visibilidade_min_m": 300.0,
      "risco_neblina": "alto",
      "chuva_prob_max_pct": 0,
      "chuva_mm_total": 0.0,
      "chuva_mm_madrugada_antes": 0.0,
      "vento_med_kmh": 3.2,
      "rajada_max_kmh": 14.4,
      "vento_dir_graus": 331,
      "vento_dir_cardeal": "NO",
      "nascer_do_sol": "06:33",
      "ok": true
    },
    "grumari": {
      "nome": "Grumari",
      "temp_min_c": 18,
      "temp_max_janela_c": 19,
      "temp_med_c": 18,
      "sensacao_min_c": 19,
      "sensacao_largada_c": 19,
      "sensacao_final_c": 21,
      "umidade_max_pct": 98,
      "visibilidade_min_m": 120.0,
      "risco_neblina": "alto",
      "chuva_prob_max_pct": 0,
      "chuva_mm_total": 0.0,
      "chuva_mm_madrugada_antes": 0.0,
      "vento_med_kmh": 5.3,
      "rajada_max_kmh": 13.3,
      "vento_dir_graus": 341,
      "vento_dir_cardeal": "N",
      "nascer_do_sol": "06:35",
      "ok": true
    }
  }
}